llm_session/__init__.py
llm_session/automator.py
llm_session/browser.py
llm_session/config.py
llm_session/exceptions.py
llm_session/providers/__init__.py
llm_session/providers/aistudio.py
llm_session/providers/base.py
llm_session/providers/chatgpt.py
llm_session/providers/claude.py
llm_session-0.1.8.dist-info/licenses/LICENSE
llm_session-0.1.8.dist-info/METADATA
llm_session-0.1.8.dist-info/WHEEL
llm_session-0.1.8.dist-info/top_level.txt
llm_session-0.1.8.dist-info/RECORD
