Metadata-Version: 2.4
Name: llm_session
Version: 0.1.8
Summary: A zero-configuration tool to automate web-based LLM interactions.
Author-email: LLM_Session <shoaib.star.a@gmail.com>
License: MIT
Project-URL: Homepage, https://github.com/star-173/llm_session
Classifier: Programming Language :: Python :: 3
Classifier: License :: OSI Approved :: MIT License
Classifier: Operating System :: OS Independent
Requires-Python: >=3.8
License-File: LICENSE
Requires-Dist: playwright>=1.30.0
Requires-Dist: appdirs>=1.4.4
Provides-Extra: test
Requires-Dist: pytest>=7.0.0; extra == "test"
Requires-Dist: pytest-mock>=3.10.0; extra == "test"
Requires-Dist: pytest-playwright>=0.3.0; extra == "test"
Dynamic: license-file
